{
  "models": [
    {
      "name": "MATE x7",
      "prices": {
        "1": 1,
        "11": 1,
        "12": 1,
        "4": 1,
        "5": 260,
        "6": 150
      }
    },
    {
      "name": "MATE x5",
      "prices": {
        "1": 3800,
        "11": 3000,
        "12": 1400,
        "4": 1200,
        "5": 400,
        "6": 200
      }
    },
    {
      "name": "MATE X3",
      "prices": {
        "1": 1900,
        "11": 1600,
        "12": 1100,
        "4": 800,
        "5": 200,
        "6": 130
      }
    },
    {
      "name": "matex25G典藏版",
      "prices": {
        "1": 1400,
        "11": 450,
        "12": 800,
        "4": 250,
        "5": 250,
        "6": 250
      }
    },
    {
      "name": "Mate X25G",
      "prices": {
        "1": 500,
        "11": 500,
        "12": 220,
        "4": 220,
        "5": 220,
        "6": 220
      }
    },
    {
      "name": "MATE   XS2",
      "prices": {
        "1": 500,
        "11": 500,
        "12": 150,
        "4": 150,
        "5": 150,
        "6": 150
      }
    },
    {
      "name": "MATE XS 5G",
      "prices": {
        "1": 500,
        "11": 500,
        "12": 150,
        "4": 150,
        "5": 150,
        "6": 150
      }
    },
    {
      "name": "Mate X5G",
      "prices": {
        "1": 400,
        "11": 400,
        "12": 150,
        "4": 150,
        "5": 150,
        "6": 150
      }
    },
    {
      "name": "novaflip",
      "prices": {
        "1": 900,
        "11": 800,
        "12": 450,
        "4": 350,
        "5": 90,
        "6": 90
      }
    },
    {
      "name": "荣耀magic v",
      "prices": {
        "1": 250,
        "11": 250,
        "12": 250,
        "4": 240,
        "5": 240,
        "6": 240
      }
    },
    {
      "name": "荣耀magic vs2",
      "prices": {
        "1": 1300,
        "11": 1100,
        "12": 600,
        "4": 260,
        "5": 260,
        "6": 260
      }
    },
    {
      "name": "荣耀magic vs",
      "prices": {
        "1": 1000,
        "11": 800,
        "12": 240,
        "4": 240,
        "5": 240,
        "6": 240
      }
    },
    {
      "name": "荣耀magic v2",
      "prices": {
        "1": 900,
        "4": 280,
        "5": 280,
        "6": 280
      }
    },
    {
      "name": "荣耀magicvs3",
      "prices": {
        "1": 550,
        "4": 400,
        "5": 240,
        "6": 240
      }
    },
    {
      "name": "荣耀magicv3",
      "prices": {
        "1": 1000,
        "4": 240,
        "5": 240,
        "6": 240
      }
    },
    {
      "name": "荣耀magic v flip",
      "prices": {
        "1": 1000,
        "11": 900,
        "12": 240,
        "4": 240,
        "5": 240,
        "6": 240
      }
    },
    {
      "name": "pocket2",
      "prices": {
        "1": 800,
        "11": 750,
        "12": 400,
        "4": 300,
        "5": 190,
        "6": 190
      }
    },
    {
      "name": "Pocket S4G",
      "prices": {
        "1": 450,
        "11": 400,
        "12": 260,
        "4": 260,
        "5": 260,
        "6": 260
      }
    },
    {
      "name": "p50pocket",
      "prices": {
        "1": 450,
        "11": 400,
        "12": 200,
        "4": 200,
        "5": 200,
        "6": 200
      }
    },
    {
      "name": "MATE70Pro",
      "prices": {
        "1": 1600,
        "11": 1500,
        "12": 1100,
        "4": 800,
        "5": 260,
        "6": 150
      }
    },
    {
      "name": "MATE 60 RS\n非凡大师版",
      "prices": {
        "1": 2300,
        "11": 2100,
        "12": 1800,
        "4": 1500,
        "5": 260,
        "6": 150
      }
    },
    {
      "name": "MATE60 Pro+",
      "prices": {
        "1": 1400,
        "11": 1300,
        "12": 900,
        "4": 800,
        "5": 220,
        "6": 220
      }
    },
    {
      "name": "MATE60 Pro",
      "prices": {
        "1": 1300,
        "11": 1200,
        "12": 800,
        "4": 600,
        "5": 220,
        "6": 220
      }
    },
    {
      "name": "MATE60",
      "prices": {
        "1": 800,
        "11": 700,
        "12": 500,
        "4": 400,
        "5": 220,
        "6": 220
      }
    },
    {
      "name": "MATE 50 RS保时捷4G",
      "prices": {
        "1": 1200,
        "11": 1000,
        "12": 800,
        "4": 600,
        "5": 190,
        "6": 190
      }
    },
    {
      "name": "MATE 50 Pro 4G",
      "prices": {
        "1": 400,
        "11": 350,
        "12": 280,
        "4": 200,
        "5": 190,
        "6": 190
      }
    },
    {
      "name": "MATE  50 4G",
      "prices": {
        "1": 300,
        "11": 300,
        "12": 280,
        "4": 220,
        "5": 190,
        "6": 190
      }
    },
    {
      "name": "MATE 50E 4G",
      "prices": {
        "1": 240,
        "11": 240,
        "12": 220,
        "4": 220,
        "5": 190,
        "6": 190
      }
    },
    {
      "name": "Mate40PRO+",
      "prices": {
        "1": 380,
        "11": 380,
        "12": 180,
        "4": 180,
        "5": 125,
        "6": 125
      }
    },
    {
      "name": "Mate40PRO5G\n(8+256)",
      "prices": {
        "1": 500,
        "11": 500,
        "12": 160,
        "4": 160,
        "5": 160,
        "6": 160
      }
    },
    {
      "name": "Mate40PRO5G\n(8+128)",
      "prices": {
        "1": 400,
        "11": 400,
        "12": 130,
        "4": 130,
        "5": 130,
        "6": 130
      }
    },
    {
      "name": "Mate40PRO4G",
      "prices": {
        "1": 350,
        "11": 350,
        "12": 130,
        "4": 130,
        "5": 130,
        "6": 130
      }
    },
    {
      "name": "Mate40 Rs保时捷(12+256/12+512)",
      "prices": {
        "1": 520,
        "11": 520,
        "12": 320,
        "4": 280,
        "5": 160,
        "6": 160
      }
    },
    {
      "name": "Mate40 Rs保时捷(8+256)",
      "prices": {
        "1": 360,
        "11": 360,
        "12": 160,
        "4": 160,
        "5": 160,
        "6": 160
      }
    },
    {
      "name": "Mate40E 5G",
      "prices": {
        "1": 260,
        "11": 260,
        "12": 160,
        "4": 160,
        "5": 160,
        "6": 160
      }
    },
    {
      "name": "Mate40",
      "prices": {
        "1": 260,
        "11": 260,
        "12": 140,
        "4": 140,
        "5": 140,
        "6": 140
      }
    },
    {
      "name": "Mate30pro 5G",
      "prices": {
        "1": 400,
        "11": 400,
        "12": 150,
        "4": 150,
        "5": 150,
        "6": 150
      }
    },
    {
      "name": "Mate30pro 4G",
      "prices": {
        "1": 400,
        "11": 400,
        "12": 150,
        "4": 150,
        "5": 150,
        "6": 150
      }
    },
    {
      "name": "Mate30 RS保时捷",
      "prices": {
        "1": 550,
        "11": 500,
        "12": 220,
        "4": 220,
        "5": 220,
        "6": 220
      }
    },
    {
      "name": "Mate30Epro 5G",
      "prices": {
        "1": 400,
        "11": 400,
        "12": 150,
        "4": 150,
        "5": 150,
        "6": 150
      }
    },
    {
      "name": "Mate305G高配",
      "prices": {
        "1": 250,
        "11": 250,
        "12": 150,
        "4": 150,
        "5": 150,
        "6": 150
      }
    },
    {
      "name": "Mate305G低配",
      "prices": {
        "1": 190,
        "11": 190,
        "12": 150,
        "4": 150,
        "5": 150,
        "6": 150
      }
    },
    {
      "name": "Mate304G高配",
      "prices": {
        "1": 190,
        "11": 190,
        "12": 150,
        "4": 150,
        "5": 150,
        "6": 150
      }
    },
    {
      "name": "Mate304G低配",
      "prices": {
        "1": 190,
        "11": 190,
        "12": 100,
        "4": 100,
        "5": 100,
        "6": 100
      }
    },
    {
      "name": "Mate20 Rs保时捷",
      "prices": {
        "1": 220,
        "11": 220,
        "12": 220,
        "4": 220,
        "5": 220,
        "6": 220
      }
    },
    {
      "name": "Mate20 Pro(8+256)",
      "prices": {
        "1": 150,
        "11": 150,
        "12": 150,
        "4": 150,
        "5": 150,
        "6": 150
      }
    },
    {
      "name": "Mate20 pro(8+128)",
      "prices": {
        "1": 130,
        "11": 130,
        "12": 130,
        "4": 130,
        "5": 130,
        "6": 130
      }
    },
    {
      "name": "Mate20 pro(6+128)",
      "prices": {
        "1": 90,
        "11": 90,
        "12": 90,
        "4": 90,
        "5": 90,
        "6": 90
      }
    },
    {
      "name": "Mate20(6+128)",
      "prices": {
        "1": 90,
        "11": 90,
        "12": 90,
        "4": 90,
        "5": 90,
        "6": 90
      }
    },
    {
      "name": "Mate20(6+64)",
      "prices": {
        "1": 70,
        "11": 70,
        "12": 70,
        "4": 70,
        "5": 70,
        "6": 70
      }
    },
    {
      "name": "Mate20x(8+256)",
      "prices": {
        "1": 180,
        "11": 180,
        "12": 160,
        "4": 160,
        "5": 160,
        "6": 160
      }
    },
    {
      "name": "Mate20x(8+128)",
      "prices": {
        "1": 130,
        "11": 130,
        "12": 90,
        "4": 90,
        "5": 90,
        "6": 90
      }
    },
    {
      "name": "Mate10pro",
      "prices": {
        "1": 80,
        "11": 80,
        "12": 80,
        "4": 80,
        "5": 80,
        "6": 80
      }
    },
    {
      "name": "Mate10",
      "prices": {
        "1": 80,
        "11": 80,
        "12": 80,
        "4": 80,
        "5": 80,
        "6": 80
      }
    },
    {
      "name": "Mate9保时捷版",
      "prices": {
        "1": 90,
        "11": 90,
        "12": 90,
        "4": 90,
        "5": 90,
        "6": 90
      }
    },
    {
      "name": "Mate9pro",
      "prices": {
        "1": 90,
        "11": 90,
        "12": 90,
        "4": 90,
        "5": 90,
        "6": 90
      }
    },
    {
      "name": "Mate 9",
      "prices": {
        "1": 70,
        "11": 70,
        "12": 70,
        "4": 70,
        "5": 70,
        "6": 70
      }
    },
    {
      "name": "Mate8(4+64)",
      "prices": {
        "1": 75,
        "11": 75,
        "12": 75,
        "4": 75,
        "5": 75,
        "6": 75
      }
    },
    {
      "name": "Mate8(3+32)",
      "prices": {
        "1": 45,
        "11": 45,
        "12": 45,
        "4": 45,
        "5": 45,
        "6": 45
      }
    },
    {
      "name": "MateRs",
      "prices": {
        "1": 80,
        "11": 80,
        "12": 80,
        "4": 80,
        "5": 80,
        "6": 80
      }
    },
    {
      "name": "Mate S",
      "prices": {
        "1": 45,
        "11": 45,
        "12": 45,
        "4": 45,
        "5": 45,
        "6": 45
      }
    },
    {
      "name": "Mate40E 4G",
      "prices": {
        "1": 260,
        "11": 260,
        "12": 160,
        "4": 160,
        "5": 160,
        "6": 160
      }
    },
    {
      "name": "P70ultra",
      "prices": {
        "1": 1400,
        "11": 1300,
        "12": 900,
        "4": 600,
        "5": 130,
        "6": 130
      }
    },
    {
      "name": "p70pro+",
      "prices": {
        "1": 1300,
        "11": 1200,
        "12": 800,
        "4": 500,
        "5": 140,
        "6": 140
      }
    },
    {
      "name": "p70pro",
      "prices": {
        "1": 1200,
        "11": 1100,
        "12": 700,
        "4": 500,
        "5": 140,
        "6": 140
      }
    },
    {
      "name": "p70",
      "prices": {
        "1": 1000,
        "11": 900,
        "12": 600,
        "4": 500,
        "5": 140,
        "6": 140
      }
    },
    {
      "name": "p60Art",
      "prices": {
        "1": 800,
        "11": 700,
        "12": 500,
        "4": 400,
        "5": 220,
        "6": 220
      }
    },
    {
      "name": "p60pro",
      "prices": {
        "1": 700,
        "11": 600,
        "12": 240,
        "4": 200,
        "5": 200,
        "6": 200
      }
    },
    {
      "name": "p60(8+256/8+512)",
      "prices": {
        "1": 350,
        "11": 300,
        "12": 200,
        "4": 200,
        "5": 200,
        "6": 200
      }
    },
    {
      "name": "p60(8+128)",
      "prices": {
        "1": 300,
        "11": 260,
        "12": 200,
        "4": 200,
        "5": 200,
        "6": 200
      }
    },
    {
      "name": "p50pro(8+256/8+512)",
      "prices": {
        "1": 200,
        "11": 200,
        "12": 200,
        "4": 200,
        "5": 200,
        "6": 200
      }
    },
    {
      "name": "p50pro(8+128)",
      "prices": {
        "1": 220,
        "11": 200,
        "12": 200,
        "4": 200,
        "5": 200,
        "6": 200
      }
    },
    {
      "name": "P50E4G",
      "prices": {
        "1": 260,
        "11": 220,
        "12": 160,
        "4": 160,
        "5": 160,
        "6": 160
      }
    },
    {
      "name": "P50",
      "prices": {
        "1": 260,
        "11": 220,
        "12": 200,
        "4": 200,
        "5": 200,
        "6": 200
      }
    },
    {
      "name": "P40 pro+",
      "prices": {
        "1": 350,
        "11": 350,
        "12": 130,
        "4": 130,
        "5": 130,
        "6": 130
      }
    },
    {
      "name": "P40 pro(8+256)",
      "prices": {
        "1": 350,
        "11": 350,
        "12": 130,
        "4": 130,
        "5": 130,
        "6": 130
      }
    },
    {
      "name": "P40 pro(8+128)",
      "prices": {
        "1": 350,
        "11": 350,
        "12": 130,
        "4": 130,
        "5": 130,
        "6": 130
      }
    },
    {
      "name": "P40(8+256)",
      "prices": {
        "1": 260,
        "11": 260,
        "12": 160,
        "4": 160,
        "5": 160,
        "6": 160
      }
    },
    {
      "name": "P40(8+128)",
      "prices": {
        "1": 330,
        "11": 330,
        "12": 130,
        "4": 130,
        "5": 130,
        "6": 130
      }
    },
    {
      "name": "P40(6+128)",
      "prices": {
        "1": 260,
        "11": 260,
        "12": 90,
        "4": 90,
        "5": 90,
        "6": 90
      }
    },
    {
      "name": "P30(8+256)",
      "prices": {
        "1": 230,
        "11": 230,
        "12": 160,
        "4": 160,
        "5": 160,
        "6": 160
      }
    },
    {
      "name": "P30(8+128)",
      "prices": {
        "1": 170,
        "11": 170,
        "12": 130,
        "4": 130,
        "5": 130,
        "6": 130
      }
    },
    {
      "name": "P30(6+128/8+64)",
      "prices": {
        "1": 120,
        "11": 120,
        "12": 90,
        "4": 90,
        "5": 90,
        "6": 90
      }
    },
    {
      "name": "P30pro",
      "prices": {
        "1": 130,
        "11": 130,
        "12": 130,
        "4": 130,
        "5": 130,
        "6": 130
      }
    },
    {
      "name": "P20pro",
      "prices": {
        "1": 75,
        "11": 75,
        "12": 75,
        "4": 75,
        "5": 75,
        "6": 75
      }
    },
    {
      "name": "P20",
      "prices": {
        "1": 75,
        "11": 75,
        "12": 75,
        "4": 75,
        "5": 75,
        "6": 75
      }
    },
    {
      "name": "P10plus",
      "prices": {
        "1": 75,
        "11": 75,
        "12": 75,
        "4": 75,
        "5": 75,
        "6": 75
      }
    },
    {
      "name": "P10",
      "prices": {
        "1": 75,
        "11": 75,
        "12": 75,
        "4": 75,
        "5": 75,
        "6": 75
      }
    },
    {
      "name": "P9(4+64)",
      "prices": {
        "1": 75,
        "11": 75,
        "12": 75,
        "4": 75,
        "5": 75,
        "6": 75
      }
    },
    {
      "name": "P9(3+32)",
      "prices": {
        "1": 35,
        "11": 35,
        "12": 35,
        "4": 35,
        "5": 35,
        "6": 35
      }
    },
    {
      "name": "P9plus",
      "prices": {
        "1": 75,
        "11": 75,
        "12": 75,
        "4": 75,
        "5": 75,
        "6": 75
      }
    },
    {
      "name": "Hi畅享80pro",
      "prices": {
        "1": 200,
        "11": 200,
        "12": 200,
        "4": 200,
        "5": 150,
        "6": 150
      }
    },
    {
      "name": "Hi畅享80",
      "prices": {
        "1": 200,
        "11": 200,
        "12": 200,
        "4": 200,
        "5": 150,
        "6": 150
      }
    },
    {
      "name": "Hi畅享70pro",
      "prices": {
        "1": 180,
        "11": 180,
        "12": 180,
        "4": 180,
        "5": 180,
        "6": 180
      }
    },
    {
      "name": "Hi畅享70plus",
      "prices": {
        "1": 260,
        "11": 260,
        "12": 260,
        "4": 260,
        "5": 260,
        "6": 260
      }
    },
    {
      "name": "Hi畅享70",
      "prices": {
        "1": 180,
        "11": 180,
        "12": 180,
        "4": 180,
        "5": 180,
        "6": 180
      }
    },
    {
      "name": "Hi畅享60 pro",
      "prices": {
        "1": 180,
        "11": 180,
        "12": 180,
        "4": 180,
        "5": 180,
        "6": 180
      }
    },
    {
      "name": "Hi畅享60",
      "prices": {
        "1": 110,
        "11": 110,
        "12": 110,
        "4": 110,
        "5": 110,
        "6": 110
      }
    },
    {
      "name": "Hi Nova12 SE",
      "prices": {
        "1": 260,
        "11": 260,
        "12": 260,
        "4": 260,
        "5": 260,
        "6": 260
      }
    },
    {
      "name": "Hi Nova 115G",
      "prices": {
        "1": 260,
        "11": 260,
        "12": 260,
        "4": 260,
        "5": 260,
        "6": 260
      }
    },
    {
      "name": "Hi nova 11se",
      "prices": {
        "1": 180,
        "11": 180,
        "12": 180,
        "4": 180,
        "5": 180,
        "6": 180
      }
    },
    {
      "name": "Hi nova 10PRO",
      "prices": {
        "1": 180,
        "11": 180,
        "12": 180,
        "4": 180,
        "5": 180,
        "6": 180
      }
    },
    {
      "name": "HI Nova10se",
      "prices": {
        "1": 180,
        "11": 180,
        "12": 180,
        "4": 180,
        "5": 180,
        "6": 180
      }
    },
    {
      "name": "Hi nova 10",
      "prices": {
        "1": 180,
        "11": 180,
        "12": 180,
        "4": 180,
        "5": 180,
        "6": 180
      }
    },
    {
      "name": "HI Nova9 Pro(8+128)",
      "prices": {
        "1": 160,
        "11": 160,
        "12": 160,
        "4": 160,
        "5": 160,
        "6": 160
      }
    },
    {
      "name": "HI Nova9 Pro(8+256)",
      "prices": {
        "1": 260,
        "11": 260,
        "12": 260,
        "4": 260,
        "5": 260,
        "6": 260
      }
    },
    {
      "name": "HI Nova9(8+128)",
      "prices": {
        "1": 160,
        "11": 160,
        "12": 160,
        "4": 160,
        "5": 160,
        "6": 160
      }
    },
    {
      "name": "HINova9(8+256)",
      "prices": {
        "1": 260,
        "11": 260,
        "12": 260,
        "4": 260,
        "5": 260,
        "6": 260
      }
    },
    {
      "name": "HINova9 se",
      "prices": {
        "1": 180,
        "11": 180,
        "12": 180,
        "4": 180,
        "5": 180,
        "6": 180
      }
    },
    {
      "name": "HI Nova9Z",
      "prices": {
        "1": 160,
        "11": 160,
        "12": 160,
        "4": 160,
        "5": 160,
        "6": 160
      }
    },
    {
      "name": "nova13",
      "prices": {
        "1": 200,
        "11": 200,
        "12": 90,
        "4": 90,
        "5": 90,
        "6": 90
      }
    },
    {
      "name": "nova13pro",
      "prices": {
        "1": 300,
        "11": 300,
        "12": 90,
        "4": 90,
        "5": 90,
        "6": 90
      }
    },
    {
      "name": "nova14",
      "prices": {
        "1": 550,
        "11": 500,
        "12": 400,
        "4": 400,
        "5": 90,
        "6": 90
      }
    },
    {
      "name": "nova12ultra",
      "prices": {
        "1": 600,
        "11": 600,
        "12": 220,
        "4": 220,
        "5": 220,
        "6": 220
      }
    },
    {
      "name": "nova12pro(12+512)",
      "prices": {
        "1": 500,
        "11": 400,
        "12": 200,
        "4": 200,
        "5": 200,
        "6": 200
      }
    },
    {
      "name": "nova12pro(12+256)",
      "prices": {
        "1": 500,
        "11": 400,
        "12": 280,
        "4": 280,
        "5": 280,
        "6": 280
      }
    },
    {
      "name": "nova12活力版",
      "prices": {
        "1": 280,
        "11": 280,
        "12": 280,
        "4": 280,
        "5": 280,
        "6": 280
      }
    },
    {
      "name": "nova12(8+512)",
      "prices": {
        "1": 200,
        "11": 200,
        "12": 200,
        "4": 200,
        "5": 200,
        "6": 200
      }
    },
    {
      "name": "nova12(8+256)",
      "prices": {
        "1": 280,
        "11": 280,
        "12": 280,
        "4": 280,
        "5": 280,
        "6": 280
      }
    },
    {
      "name": "Nova 11 Ultra 4G",
      "prices": {
        "1": 200,
        "11": 200,
        "12": 200,
        "4": 200,
        "5": 200,
        "6": 200
      }
    },
    {
      "name": "Nova 11 PRO4G",
      "prices": {
        "1": 200,
        "11": 200,
        "12": 200,
        "4": 200,
        "5": 200,
        "6": 200
      }
    },
    {
      "name": "nova11(8+256)",
      "prices": {
        "1": 170,
        "11": 170,
        "12": 170,
        "4": 170,
        "5": 170,
        "6": 170
      }
    },
    {
      "name": "nova11(8+512)",
      "prices": {
        "1": 260,
        "11": 260,
        "12": 260,
        "4": 260,
        "5": 260,
        "6": 260
      }
    },
    {
      "name": "nove11se(8+256)",
      "prices": {
        "1": 260,
        "11": 260,
        "12": 260,
        "4": 260,
        "5": 260,
        "6": 260
      }
    },
    {
      "name": "nove11se(8+128)",
      "prices": {
        "1": 170,
        "11": 170,
        "12": 170,
        "4": 170,
        "5": 170,
        "6": 170
      }
    },
    {
      "name": "nova10pro(8+256)",
      "prices": {
        "1": 260,
        "11": 260,
        "12": 260,
        "4": 260,
        "5": 260,
        "6": 260
      }
    },
    {
      "name": "nova10pro(8+128)",
      "prices": {
        "1": 170,
        "11": 170,
        "12": 170,
        "4": 170,
        "5": 170,
        "6": 170
      }
    },
    {
      "name": "Nova10se(8+256)",
      "prices": {
        "1": 260,
        "11": 260,
        "12": 260,
        "4": 260,
        "5": 260,
        "6": 260
      }
    },
    {
      "name": "Nova10se(8+128)",
      "prices": {
        "1": 170,
        "11": 170,
        "12": 170,
        "4": 170,
        "5": 170,
        "6": 170
      }
    },
    {
      "name": "Nova 10Z",
      "prices": {
        "1": 170,
        "11": 170,
        "12": 170,
        "4": 170,
        "5": 170,
        "6": 170
      }
    },
    {
      "name": "nova10青春",
      "prices": {
        "1": 200,
        "11": 200,
        "12": 200,
        "4": 200,
        "5": 200,
        "6": 200
      }
    },
    {
      "name": "nova10(8+256)",
      "prices": {
        "1": 260,
        "11": 260,
        "12": 260,
        "4": 260,
        "5": 260,
        "6": 260
      }
    },
    {
      "name": "nova10(8+128)",
      "prices": {
        "1": 170,
        "11": 170,
        "12": 170,
        "4": 170,
        "5": 170,
        "6": 170
      }
    },
    {
      "name": "Nova9 Pro(8+256)",
      "prices": {
        "1": 260,
        "11": 260,
        "12": 260,
        "4": 260,
        "5": 260,
        "6": 260
      }
    },
    {
      "name": "Nova9 Pro(8+128)",
      "prices": {
        "1": 170,
        "11": 170,
        "12": 170,
        "4": 170,
        "5": 170,
        "6": 170
      }
    },
    {
      "name": "nova9se",
      "prices": {
        "1": 200,
        "11": 200,
        "12": 200,
        "4": 200,
        "5": 200,
        "6": 200
      }
    },
    {
      "name": "Nova9(8+256)",
      "prices": {
        "1": 260,
        "11": 260,
        "12": 260,
        "4": 260,
        "5": 260,
        "6": 260
      }
    },
    {
      "name": "Nova9(8+128)",
      "prices": {
        "1": 170,
        "11": 170,
        "12": 170,
        "4": 170,
        "5": 170,
        "6": 170
      }
    },
    {
      "name": "Nova8 Pro 5G",
      "prices": {
        "1": 170,
        "11": 170,
        "12": 170,
        "4": 170,
        "5": 170,
        "6": 170
      }
    },
    {
      "name": "Nova8 Pro 4G",
      "prices": {
        "1": 170,
        "11": 170,
        "12": 170,
        "4": 170,
        "5": 170,
        "6": 170
      }
    },
    {
      "name": "Nova8 se5G",
      "prices": {
        "1": 170,
        "11": 170,
        "12": 170,
        "4": 170,
        "5": 170,
        "6": 170
      }
    },
    {
      "name": "Nova8 se4G",
      "prices": {
        "1": 170,
        "11": 170,
        "12": 170,
        "4": 170,
        "5": 170,
        "6": 170
      }
    },
    {
      "name": "Nova8se活力版",
      "prices": {
        "1": 170,
        "11": 170,
        "12": 170,
        "4": 170,
        "5": 170,
        "6": 170
      }
    },
    {
      "name": "Nova8",
      "prices": {
        "1": 170,
        "11": 170,
        "12": 170,
        "4": 170,
        "5": 170,
        "6": 170
      }
    },
    {
      "name": "Nova7pro",
      "prices": {
        "1": 220,
        "11": 220,
        "12": 220,
        "4": 220,
        "5": 220,
        "6": 220
      }
    },
    {
      "name": "Nova75G",
      "prices": {
        "1": 220,
        "11": 220,
        "12": 220,
        "4": 220,
        "5": 220,
        "6": 220
      }
    },
    {
      "name": "Nova7se活力版",
      "prices": {
        "1": 160,
        "11": 160,
        "12": 160,
        "4": 160,
        "5": 160,
        "6": 160
      }
    },
    {
      "name": "nova7se乐活版",
      "prices": {
        "1": 220,
        "11": 220,
        "12": 220,
        "4": 220,
        "5": 220,
        "6": 220
      }
    },
    {
      "name": "Nova7se",
      "prices": {
        "1": 220,
        "11": 220,
        "12": 220,
        "4": 220,
        "5": 220,
        "6": 220
      }
    },
    {
      "name": "Nova65G",
      "prices": {
        "1": 130,
        "11": 130,
        "12": 130,
        "4": 130,
        "5": 130,
        "6": 130
      }
    },
    {
      "name": "Nova64G",
      "prices": {
        "1": 130,
        "11": 130,
        "12": 130,
        "4": 130,
        "5": 130,
        "6": 130
      }
    },
    {
      "name": "Nova6 se",
      "prices": {
        "1": 220,
        "11": 220,
        "12": 220,
        "4": 220,
        "5": 220,
        "6": 220
      }
    },
    {
      "name": "Nova5pro",
      "prices": {
        "1": 130,
        "11": 130,
        "12": 130,
        "4": 130,
        "5": 130,
        "6": 130
      }
    },
    {
      "name": "Nova5i(8+128)",
      "prices": {
        "1": 220,
        "11": 220,
        "12": 220,
        "4": 220,
        "5": 220,
        "6": 220
      }
    },
    {
      "name": "Nova5i(6+128)",
      "prices": {
        "1": 150,
        "11": 150,
        "12": 150,
        "4": 150,
        "5": 150,
        "6": 150
      }
    },
    {
      "name": "Nova5ipro(8+128)",
      "prices": {
        "1": 220,
        "11": 220,
        "12": 220,
        "4": 220,
        "5": 220,
        "6": 220
      }
    },
    {
      "name": "Nova5ipro(6+128)",
      "prices": {
        "1": 150,
        "11": 150,
        "12": 150,
        "4": 150,
        "5": 150,
        "6": 150
      }
    },
    {
      "name": "Nova5ipro(8+256)",
      "prices": {
        "1": 220,
        "11": 220,
        "12": 220,
        "4": 220,
        "5": 220,
        "6": 220
      }
    },
    {
      "name": "Nova5z",
      "prices": {
        "1": 130,
        "11": 130,
        "12": 130,
        "4": 130,
        "5": 130,
        "6": 130
      }
    },
    {
      "name": "Nova5",
      "prices": {
        "1": 220,
        "11": 220,
        "12": 220,
        "4": 220,
        "5": 220,
        "6": 220
      }
    },
    {
      "name": "Nova4(8+128)",
      "prices": {
        "1": 130,
        "11": 130,
        "12": 130,
        "4": 130,
        "5": 130,
        "6": 130
      }
    },
    {
      "name": "Nova4(6+128)",
      "prices": {
        "1": 90,
        "11": 90,
        "12": 90,
        "4": 90,
        "5": 90,
        "6": 90
      }
    },
    {
      "name": "Nova4e",
      "prices": {
        "1": 160,
        "11": 160,
        "12": 160,
        "4": 160,
        "5": 160,
        "6": 160
      }
    },
    {
      "name": "Nova3(6+128)",
      "prices": {
        "1": 90,
        "11": 90,
        "12": 90,
        "4": 90,
        "5": 90,
        "6": 90
      }
    },
    {
      "name": "Nova3(6+64)",
      "prices": {
        "1": 80,
        "11": 80,
        "12": 80,
        "4": 80,
        "5": 80,
        "6": 80
      }
    },
    {
      "name": "Nova3e",
      "prices": {
        "1": 90,
        "11": 90,
        "12": 90,
        "4": 90,
        "5": 90,
        "6": 90
      }
    },
    {
      "name": "Nova3i",
      "prices": {
        "1": 120,
        "11": 120,
        "12": 120,
        "4": 120,
        "5": 120,
        "6": 120
      }
    },
    {
      "name": "Nova2plus",
      "prices": {
        "1": 100,
        "11": 100,
        "12": 100,
        "4": 100,
        "5": 100,
        "6": 100
      }
    },
    {
      "name": "Nova2s",
      "prices": {
        "1": 90,
        "11": 90,
        "12": 90,
        "4": 90,
        "5": 90,
        "6": 90
      }
    },
    {
      "name": "Nova2",
      "prices": {
        "1": 85,
        "11": 85,
        "12": 85,
        "4": 85,
        "5": 85,
        "6": 85
      }
    },
    {
      "name": "Nova青春",
      "prices": {
        "1": 85,
        "11": 85,
        "12": 85,
        "4": 85,
        "5": 85,
        "6": 85
      }
    },
    {
      "name": "Nova  (4+64)",
      "prices": {
        "1": 120,
        "11": 120,
        "12": 120,
        "4": 120,
        "5": 120,
        "6": 120
      }
    },
    {
      "name": "Nova(3+32)",
      "prices": {
        "1": 55,
        "11": 55,
        "12": 55,
        "4": 55,
        "5": 55,
        "6": 55
      }
    },
    {
      "name": "优畅享50 Plus 5G",
      "prices": {
        "1": 200,
        "11": 200,
        "12": 200,
        "4": 200,
        "5": 200,
        "6": 200
      }
    },
    {
      "name": "优畅享50Pro",
      "prices": {
        "1": 200,
        "11": 200,
        "12": 200,
        "4": 200,
        "5": 200,
        "6": 200
      }
    },
    {
      "name": "优畅享50",
      "prices": {
        "1": 140,
        "11": 140,
        "12": 140,
        "4": 140,
        "5": 140,
        "6": 140
      }
    },
    {
      "name": "优畅享30e",
      "prices": {
        "1": 140,
        "11": 140,
        "12": 140,
        "4": 140,
        "5": 140,
        "6": 140
      }
    },
    {
      "name": "优畅享20 plus",
      "prices": {
        "1": 150,
        "11": 150,
        "12": 150,
        "4": 150,
        "5": 150,
        "6": 150
      }
    },
    {
      "name": "优畅享20",
      "prices": {
        "1": 140,
        "11": 140,
        "12": 140,
        "4": 140,
        "5": 140,
        "6": 140
      }
    },
    {
      "name": "雷鸟",
      "prices": {
        "1": 160,
        "11": 160,
        "12": 160,
        "4": 160,
        "5": 160,
        "6": 160
      }
    },
    {
      "name": "NZONE 50Pro 5G",
      "prices": {
        "1": 160,
        "11": 160,
        "12": 160,
        "4": 160,
        "5": 160,
        "6": 160
      }
    },
    {
      "name": "智选s7pro+",
      "prices": {
        "1": 160,
        "11": 160,
        "12": 160,
        "4": 160,
        "5": 160,
        "6": 160
      }
    },
    {
      "name": "智选s7pro",
      "prices": {
        "1": 160,
        "11": 160,
        "12": 160,
        "4": 160,
        "5": 160,
        "6": 160
      }
    },
    {
      "name": "智选s7",
      "prices": {
        "1": 150,
        "11": 150,
        "12": 150,
        "4": 150,
        "5": 150,
        "6": 150
      }
    },
    {
      "name": "鼎桥P505G",
      "prices": {
        "1": 150,
        "11": 150,
        "12": 150,
        "4": 150,
        "5": 150,
        "6": 150
      }
    },
    {
      "name": "鼎桥M40",
      "prices": {
        "1": 150,
        "11": 150,
        "12": 150,
        "4": 150,
        "5": 150,
        "6": 150
      }
    },
    {
      "name": "鼎桥N8 Pro",
      "prices": {
        "1": 160,
        "11": 160,
        "12": 160,
        "4": 160,
        "5": 160,
        "6": 160
      }
    },
    {
      "name": "WIKO5G",
      "prices": {
        "1": 260,
        "11": 260,
        "12": 260,
        "4": 260,
        "5": 260,
        "6": 260
      }
    },
    {
      "name": "NEX  US",
      "prices": {
        "1": 25,
        "11": 25,
        "12": 20,
        "4": 20,
        "5": 20,
        "6": 20
      }
    },
    {
      "name": "荣耀Power",
      "prices": {
        "1": 550,
        "11": 500,
        "12": 300,
        "4": 300,
        "5": 220,
        "6": 220
      }
    },
    {
      "name": "荣耀300",
      "prices": {
        "1": 550,
        "11": 500,
        "12": 400,
        "4": 350,
        "5": 200,
        "6": 200
      }
    },
    {
      "name": "荣耀200pro",
      "prices": {
        "1": 550,
        "11": 450,
        "12": 400,
        "4": 280,
        "5": 200,
        "6": 200
      }
    },
    {
      "name": "荣耀200",
      "prices": {
        "1": 500,
        "11": 400,
        "12": 350,
        "4": 280,
        "5": 200,
        "6": 200
      }
    },
    {
      "name": "荣耀100pro",
      "prices": {
        "1": 500,
        "11": 450,
        "12": 350,
        "4": 300,
        "5": 200,
        "6": 200
      }
    },
    {
      "name": "荣耀100",
      "prices": {
        "1": 500,
        "11": 400,
        "12": 350,
        "4": 300,
        "5": 200,
        "6": 200
      }
    },
    {
      "name": "荣耀90gt",
      "prices": {
        "1": 400,
        "11": 350,
        "12": 300,
        "4": 280,
        "5": 200,
        "6": 200
      }
    },
    {
      "name": "荣耀90pro",
      "prices": {
        "1": 500,
        "11": 450,
        "12": 400,
        "4": 350,
        "5": 200,
        "6": 200
      }
    },
    {
      "name": "荣耀90",
      "prices": {
        "1": 450,
        "11": 400,
        "12": 350,
        "4": 300,
        "5": 200,
        "6": 200
      }
    },
    {
      "name": "荣耀80gt",
      "prices": {
        "1": 450,
        "11": 400,
        "12": 350,
        "4": 300,
        "5": 200,
        "6": 200
      }
    },
    {
      "name": "荣耀80se",
      "prices": {
        "1": 260,
        "11": 260,
        "12": 260,
        "4": 260,
        "5": 260,
        "6": 260
      }
    },
    {
      "name": "荣耀80Pro直屏\n版",
      "prices": {
        "1": 280,
        "11": 280,
        "12": 280,
        "4": 280,
        "5": 200,
        "6": 200
      }
    },
    {
      "name": "荣耀80 pro",
      "prices": {
        "1": 300,
        "11": 300,
        "12": 300,
        "4": 300,
        "5": 240,
        "6": 240
      }
    },
    {
      "name": "荣耀80",
      "prices": {
        "1": 260,
        "11": 260,
        "12": 260,
        "4": 260,
        "5": 200,
        "6": 200
      }
    },
    {
      "name": "荣耀70 Pro",
      "prices": {
        "1": 200,
        "11": 200,
        "12": 200,
        "4": 200,
        "5": 200,
        "6": 200
      }
    },
    {
      "name": "荣耀70",
      "prices": {
        "1": 260,
        "11": 260,
        "12": 260,
        "4": 260,
        "5": 260,
        "6": 260
      }
    },
    {
      "name": "荣耀60 Pro",
      "prices": {
        "1": 260,
        "11": 260,
        "12": 260,
        "4": 260,
        "5": 260,
        "6": 260
      }
    },
    {
      "name": "荣耀60 SE",
      "prices": {
        "1": 260,
        "11": 260,
        "12": 260,
        "4": 260,
        "5": 260,
        "6": 260
      }
    },
    {
      "name": "荣耀60",
      "prices": {
        "1": 220,
        "11": 220,
        "12": 220,
        "4": 220,
        "5": 220,
        "6": 220
      }
    },
    {
      "name": "荣耀50pro",
      "prices": {
        "1": 220,
        "11": 220,
        "12": 220,
        "4": 220,
        "5": 220,
        "6": 220
      }
    },
    {
      "name": "荣耀50\n(8+256/12+256)",
      "prices": {
        "1": 220,
        "11": 220,
        "12": 220,
        "4": 220,
        "5": 220,
        "6": 220
      }
    },
    {
      "name": "荣耀50(8+128)",
      "prices": {
        "1": 160,
        "11": 160,
        "12": 160,
        "4": 160,
        "5": 160,
        "6": 160
      }
    },
    {
      "name": "荣耀50 se(12+256)",
      "prices": {
        "1": 280,
        "11": 280,
        "12": 280,
        "4": 280,
        "5": 280,
        "6": 280
      }
    },
    {
      "name": "荣耀50 se(8+256)",
      "prices": {
        "1": 260,
        "11": 260,
        "12": 260,
        "4": 260,
        "5": 260,
        "6": 260
      }
    },
    {
      "name": "荣耀50 se(8+128)",
      "prices": {
        "1": 160,
        "11": 160,
        "12": 160,
        "4": 160,
        "5": 160,
        "6": 160
      }
    },
    {
      "name": "荣耀30 Pro+",
      "prices": {
        "1": 150,
        "11": 150,
        "12": 150,
        "4": 150,
        "5": 150,
        "6": 150
      }
    },
    {
      "name": "荣耀30 Pro",
      "prices": {
        "1": 150,
        "11": 150,
        "12": 150,
        "4": 150,
        "5": 150,
        "6": 150
      }
    },
    {
      "name": "荣耀30青春高配",
      "prices": {
        "1": 160,
        "11": 160,
        "12": 160,
        "4": 160,
        "5": 160,
        "6": 160
      }
    },
    {
      "name": "荣耀30青春低配",
      "prices": {
        "1": 150,
        "11": 150,
        "12": 150,
        "4": 150,
        "5": 150,
        "6": 150
      }
    },
    {
      "name": "荣耀30s",
      "prices": {
        "1": 200,
        "11": 200,
        "12": 200,
        "4": 200,
        "5": 200,
        "6": 200
      }
    },
    {
      "name": "荣耀30",
      "prices": {
        "1": 200,
        "11": 200,
        "12": 200,
        "4": 200,
        "5": 200,
        "6": 200
      }
    },
    {
      "name": "荣耀30青春(6+64G)",
      "prices": {
        "1": 110,
        "11": 110,
        "12": 110,
        "4": 110,
        "5": 110,
        "6": 110
      }
    },
    {
      "name": "荣耀20Pro高配",
      "prices": {
        "1": 170,
        "11": 170,
        "12": 170,
        "4": 170,
        "5": 170,
        "6": 170
      }
    },
    {
      "name": "荣耀20Pro低配",
      "prices": {
        "1": 130,
        "11": 130,
        "12": 130,
        "4": 130,
        "5": 130,
        "6": 130
      }
    },
    {
      "name": "荣耀20(8+256)",
      "prices": {
        "1": 170,
        "11": 170,
        "12": 170,
        "4": 170,
        "5": 170,
        "6": 170
      }
    },
    {
      "name": "荣耀20\n(6+128/8+128)",
      "prices": {
        "1": 130,
        "11": 130,
        "12": 130,
        "4": 130,
        "5": 130,
        "6": 130
      }
    },
    {
      "name": "荣耀20青春(6+128)",
      "prices": {
        "1": 150,
        "11": 150,
        "12": 150,
        "4": 150,
        "5": 150,
        "6": 150
      }
    },
    {
      "name": "荣耀20青春(8+128)",
      "prices": {
        "1": 200,
        "11": 200,
        "12": 200,
        "4": 200,
        "5": 200,
        "6": 200
      }
    },
    {
      "name": "荣耀20青春\n(4+64、6+64)",
      "prices": {
        "1": 130,
        "11": 130,
        "12": 130,
        "4": 130,
        "5": 130,
        "6": 130
      }
    },
    {
      "name": "荣耀20s(8+128)",
      "prices": {
        "1": 200,
        "11": 200,
        "12": 200,
        "4": 200,
        "5": 200,
        "6": 200
      }
    },
    {
      "name": "荣耀20s(6+128)",
      "prices": {
        "1": 150,
        "11": 150,
        "12": 150,
        "4": 150,
        "5": 150,
        "6": 150
      }
    },
    {
      "name": "荣耀20i",
      "prices": {
        "1": 120,
        "11": 120,
        "12": 120,
        "4": 120,
        "5": 120,
        "6": 120
      }
    },
    {
      "name": "荣耀10青春",
      "prices": {
        "1": 100,
        "11": 100,
        "12": 100,
        "4": 100,
        "5": 100,
        "6": 100
      }
    },
    {
      "name": "荣耀10",
      "prices": {
        "1": 80,
        "11": 80,
        "12": 80,
        "4": 80,
        "5": 80,
        "6": 80
      }
    },
    {
      "name": "荣耀Note10",
      "prices": {
        "1": 90,
        "11": 90,
        "12": 65,
        "4": 65,
        "5": 65,
        "6": 65
      }
    },
    {
      "name": "荣耀9x pro(8+256)",
      "prices": {
        "1": 200,
        "11": 200,
        "12": 200,
        "4": 200,
        "5": 200,
        "6": 200
      }
    },
    {
      "name": "荣耀9x pro(8+128)",
      "prices": {
        "1": 200,
        "11": 200,
        "12": 200,
        "4": 200,
        "5": 200,
        "6": 200
      }
    },
    {
      "name": "荣耀9x pro(6+64)",
      "prices": {
        "1": 130,
        "11": 130,
        "12": 130,
        "4": 130,
        "5": 130,
        "6": 130
      }
    },
    {
      "name": "荣耀9x(8+128)",
      "prices": {
        "1": 200,
        "11": 200,
        "12": 200,
        "4": 200,
        "5": 200,
        "6": 200
      }
    },
    {
      "name": "荣耀9x(6+128)",
      "prices": {
        "1": 150,
        "11": 150,
        "12": 150,
        "4": 150,
        "5": 150,
        "6": 150
      }
    },
    {
      "name": "荣耀9x(6+64)",
      "prices": {
        "1": 110,
        "11": 110,
        "12": 110,
        "4": 110,
        "5": 110,
        "6": 110
      }
    },
    {
      "name": "荣耀9x(4+64)",
      "prices": {
        "1": 110,
        "11": 110,
        "12": 110,
        "4": 110,
        "5": 110,
        "6": 110
      }
    },
    {
      "name": "荣耀9i",
      "prices": {
        "1": 80,
        "11": 80,
        "12": 80,
        "4": 80,
        "5": 80,
        "6": 80
      }
    },
    {
      "name": "荣耀9青春",
      "prices": {
        "1": 75,
        "11": 75,
        "12": 75,
        "4": 75,
        "5": 75,
        "6": 75
      }
    },
    {
      "name": "荣耀9",
      "prices": {
        "1": 75,
        "11": 75,
        "12": 75,
        "4": 75,
        "5": 75,
        "6": 75
      }
    },
    {
      "name": "荣耀8X(6+128)",
      "prices": {
        "1": 120,
        "11": 120,
        "12": 120,
        "4": 120,
        "5": 120,
        "6": 120
      }
    },
    {
      "name": "荣耀8X\n(4+64/4+128/6+64)",
      "prices": {
        "1": 120,
        "11": 120,
        "12": 120,
        "4": 120,
        "5": 120,
        "6": 120
      }
    },
    {
      "name": "荣耀8青春高配",
      "prices": {
        "1": 65,
        "11": 65,
        "12": 65,
        "4": 65,
        "5": 65,
        "6": 65
      }
    },
    {
      "name": "荣耀8青春低配",
      "prices": {
        "1": 40,
        "11": 40,
        "12": 40,
        "4": 40,
        "5": 40,
        "6": 40
      }
    },
    {
      "name": "荣耀Note8",
      "prices": {
        "1": 65,
        "11": 65,
        "12": 65,
        "4": 65,
        "5": 65,
        "6": 65
      }
    },
    {
      "name": "荣耀8",
      "prices": {
        "1": 60,
        "11": 60,
        "12": 60,
        "4": 60,
        "5": 60,
        "6": 60
      }
    },
    {
      "name": "荣耀x70i",
      "prices": {
        "1": 350,
        "11": 300,
        "12": 300,
        "4": 300,
        "5": 200,
        "6": 200
      }
    },
    {
      "name": "荣耀x70",
      "prices": {
        "1": 400,
        "11": 350,
        "12": 350,
        "4": 300,
        "5": 200,
        "6": 200
      }
    },
    {
      "name": "荣耀x60pro",
      "prices": {
        "1": 450,
        "11": 400,
        "12": 400,
        "4": 300,
        "5": 200,
        "6": 200
      }
    },
    {
      "name": "荣耀x60",
      "prices": {
        "1": 400,
        "11": 350,
        "12": 350,
        "4": 280,
        "5": 200,
        "6": 200
      }
    },
    {
      "name": "荣耀x60i",
      "prices": {
        "1": 280,
        "11": 280,
        "12": 280,
        "4": 280,
        "5": 200,
        "6": 200
      }
    },
    {
      "name": "荣耀x50Pro",
      "prices": {
        "1": 350,
        "11": 300,
        "12": 300,
        "4": 300,
        "5": 200,
        "6": 200
      }
    },
    {
      "name": "荣耀x50i+",
      "prices": {
        "1": 300,
        "11": 300,
        "12": 300,
        "4": 300,
        "5": 200,
        "6": 200
      }
    },
    {
      "name": "荣耀X50i（8+256） 5G",
      "prices": {
        "1": 260,
        "11": 260,
        "12": 260,
        "4": 260,
        "5": 260,
        "6": 260
      }
    },
    {
      "name": "荣耀x50i\n（12+256）5g",
      "prices": {
        "1": 260,
        "11": 260,
        "12": 260,
        "4": 260,
        "5": 260,
        "6": 260
      }
    },
    {
      "name": "荣耀x50gt",
      "prices": {
        "1": 500,
        "11": 400,
        "12": 400,
        "4": 350,
        "5": 200,
        "6": 200
      }
    },
    {
      "name": "荣耀x50（8+256）",
      "prices": {
        "1": 260,
        "11": 260,
        "12": 260,
        "4": 260,
        "5": 260,
        "6": 260
      }
    },
    {
      "name": "荣耀x50（8+128）",
      "prices": {
        "1": 160,
        "11": 160,
        "12": 160,
        "4": 160,
        "5": 160,
        "6": 160
      }
    },
    {
      "name": "荣耀x50（12+256）",
      "prices": {
        "1": 380,
        "11": 300,
        "12": 300,
        "4": 300,
        "5": 200,
        "6": 200
      }
    },
    {
      "name": "荣耀x50（12+512）",
      "prices": {
        "1": 450,
        "11": 400,
        "12": 400,
        "4": 400,
        "5": 200,
        "6": 200
      }
    },
    {
      "name": "荣耀x40gt",
      "prices": {
        "1": 250,
        "11": 250,
        "12": 250,
        "4": 250,
        "5": 200,
        "6": 200
      }
    },
    {
      "name": "荣耀x40i（8+128）",
      "prices": {
        "1": 160,
        "11": 160,
        "12": 160,
        "4": 160,
        "5": 160,
        "6": 160
      }
    },
    {
      "name": "荣耀x40i（8+256）",
      "prices": {
        "1": 260,
        "11": 260,
        "12": 260,
        "4": 260,
        "5": 260,
        "6": 260
      }
    },
    {
      "name": "荣耀x40（8+128）",
      "prices": {
        "1": 160,
        "11": 160,
        "12": 160,
        "4": 160,
        "5": 160,
        "6": 160
      }
    },
    {
      "name": "荣耀x40（8+256）",
      "prices": {
        "1": 260,
        "11": 260,
        "12": 260,
        "4": 260,
        "5": 260,
        "6": 260
      }
    },
    {
      "name": "荣耀x40（12+256）",
      "prices": {
        "1": 260,
        "11": 260,
        "12": 260,
        "4": 260,
        "5": 260,
        "6": 260
      }
    },
    {
      "name": "荣耀x40（6+128）",
      "prices": {
        "1": 150,
        "11": 150,
        "12": 150,
        "4": 150,
        "5": 150,
        "6": 150
      }
    },
    {
      "name": "荣耀x30MAX",
      "prices": {
        "1": 160,
        "11": 160,
        "12": 160,
        "4": 160,
        "5": 160,
        "6": 160
      }
    },
    {
      "name": "荣耀x30i\n(8+128/8+256)",
      "prices": {
        "1": 180,
        "11": 180,
        "12": 180,
        "4": 180,
        "5": 180,
        "6": 180
      }
    },
    {
      "name": "荣耀x30i(6+128)",
      "prices": {
        "1": 150,
        "11": 150,
        "12": 150,
        "4": 150,
        "5": 150,
        "6": 150
      }
    },
    {
      "name": "荣耀x30(8+256)",
      "prices": {
        "1": 260,
        "11": 260,
        "12": 260,
        "4": 260,
        "5": 260,
        "6": 260
      }
    },
    {
      "name": "荣耀x30(8+128)",
      "prices": {
        "1": 160,
        "11": 160,
        "12": 160,
        "4": 160,
        "5": 160,
        "6": 160
      }
    },
    {
      "name": "荣耀x30(6+128)",
      "prices": {
        "1": 150,
        "11": 150,
        "12": 150,
        "4": 150,
        "5": 150,
        "6": 150
      }
    },
    {
      "name": "荣耀x20se(8+128)",
      "prices": {
        "1": 160,
        "11": 160,
        "12": 160,
        "4": 160,
        "5": 160,
        "6": 160
      }
    },
    {
      "name": "荣耀x20se(6+128)",
      "prices": {
        "1": 150,
        "11": 150,
        "12": 150,
        "4": 150,
        "5": 150,
        "6": 150
      }
    },
    {
      "name": "荣耀x20",
      "prices": {
        "1": 160,
        "11": 160,
        "12": 160,
        "4": 160,
        "5": 160,
        "6": 160
      }
    },
    {
      "name": "荣耀x10(8+128)",
      "prices": {
        "1": 160,
        "11": 160,
        "12": 160,
        "4": 160,
        "5": 160,
        "6": 160
      }
    },
    {
      "name": "荣耀x10(6+128)",
      "prices": {
        "1": 150,
        "11": 150,
        "12": 150,
        "4": 150,
        "5": 150,
        "6": 150
      }
    },
    {
      "name": "荣耀x10(6+64)",
      "prices": {
        "1": 100,
        "11": 100,
        "12": 100,
        "4": 100,
        "5": 100,
        "6": 100
      }
    },
    {
      "name": "荣耀X10MAX\n(8+128)",
      "prices": {
        "1": 160,
        "11": 160,
        "12": 160,
        "4": 160,
        "5": 160,
        "6": 160
      }
    },
    {
      "name": "荣耀x10max(6+128)",
      "prices": {
        "1": 150,
        "11": 150,
        "12": 150,
        "4": 150,
        "5": 150,
        "6": 150
      }
    },
    {
      "name": "荣耀x10max (6+64)",
      "prices": {
        "1": 110,
        "11": 110,
        "12": 110,
        "4": 110,
        "5": 110,
        "6": 110
      }
    },
    {
      "name": "荣耀V40轻奢版",
      "prices": {
        "1": 160,
        "11": 160,
        "12": 160,
        "4": 160,
        "5": 160,
        "6": 160
      }
    },
    {
      "name": "荣耀V40",
      "prices": {
        "1": 160,
        "11": 160,
        "12": 160,
        "4": 160,
        "5": 160,
        "6": 160
      }
    },
    {
      "name": "荣耀V30 pro",
      "prices": {
        "1": 130,
        "11": 130,
        "12": 130,
        "4": 130,
        "5": 130,
        "6": 130
      }
    },
    {
      "name": "荣耀V305G",
      "prices": {
        "1": 130,
        "11": 130,
        "12": 130,
        "4": 130,
        "5": 130,
        "6": 130
      }
    },
    {
      "name": "荣耀V20高配",
      "prices": {
        "1": 130,
        "11": 130,
        "12": 130,
        "4": 130,
        "5": 130,
        "6": 130
      }
    },
    {
      "name": "荣耀V20低配",
      "prices": {
        "1": 90,
        "11": 90,
        "12": 90,
        "4": 90,
        "5": 90,
        "6": 90
      }
    },
    {
      "name": "荣耀V10",
      "prices": {
        "1": 75,
        "11": 75,
        "12": 75,
        "4": 75,
        "5": 75,
        "6": 75
      }
    },
    {
      "name": "荣耀V9",
      "prices": {
        "1": 75,
        "11": 75,
        "12": 75,
        "4": 75,
        "5": 75,
        "6": 75
      }
    },
    {
      "name": "荣耀V8",
      "prices": {
        "1": 70,
        "11": 70,
        "12": 70,
        "4": 70,
        "5": 70,
        "6": 70
      }
    },
    {
      "name": "荣耀play9T",
      "prices": {
        "1": 220,
        "11": 220,
        "12": 220,
        "4": 220,
        "5": 220,
        "6": 220
      }
    },
    {
      "name": "荣耀play9C",
      "prices": {
        "1": 150,
        "11": 150,
        "12": 150,
        "4": 150,
        "5": 150,
        "6": 150
      }
    },
    {
      "name": "荣耀play8Tpro",
      "prices": {
        "1": 230,
        "11": 230,
        "12": 230,
        "4": 230,
        "5": 230,
        "6": 230
      }
    },
    {
      "name": "荣耀play8T",
      "prices": {
        "1": 220,
        "11": 220,
        "12": 220,
        "4": 220,
        "5": 220,
        "6": 220
      }
    },
    {
      "name": "荣耀play7Tpro",
      "prices": {
        "1": 200,
        "11": 200,
        "12": 200,
        "4": 200,
        "5": 200,
        "6": 200
      }
    },
    {
      "name": "荣耀Play7T",
      "prices": {
        "1": 160,
        "11": 160,
        "12": 160,
        "4": 160,
        "5": 160,
        "6": 160
      }
    },
    {
      "name": "荣耀Play6C",
      "prices": {
        "1": 150,
        "11": 150,
        "12": 150,
        "4": 150,
        "5": 150,
        "6": 150
      }
    },
    {
      "name": "荣耀Play6T Pro",
      "prices": {
        "1": 200,
        "11": 200,
        "12": 200,
        "4": 200,
        "5": 200,
        "6": 200
      }
    },
    {
      "name": "荣耀Play6T",
      "prices": {
        "1": 190,
        "11": 190,
        "12": 190,
        "4": 190,
        "5": 190,
        "6": 190
      }
    },
    {
      "name": "荣耀Play5T Pro",
      "prices": {
        "1": 200,
        "11": 200,
        "12": 200,
        "4": 200,
        "5": 200,
        "6": 200
      }
    },
    {
      "name": "荣耀Play5T",
      "prices": {
        "1": 200,
        "11": 200,
        "12": 200,
        "4": 200,
        "5": 200,
        "6": 200
      }
    },
    {
      "name": "荣耀Play5t活力版",
      "prices": {
        "1": 150,
        "11": 150,
        "12": 150,
        "4": 150,
        "5": 150,
        "6": 150
      }
    },
    {
      "name": "荣耀Play5活力版",
      "prices": {
        "1": 160,
        "11": 160,
        "12": 160,
        "4": 160,
        "5": 160,
        "6": 160
      }
    },
    {
      "name": "荣耀Play5(8+256)",
      "prices": {
        "1": 260,
        "11": 260,
        "12": 260,
        "4": 260,
        "5": 260,
        "6": 260
      }
    },
    {
      "name": "荣耀Play5(8+128)",
      "prices": {
        "1": 160,
        "11": 160,
        "12": 160,
        "4": 160,
        "5": 160,
        "6": 160
      }
    },
    {
      "name": "荣耀Play4t Pro",
      "prices": {
        "1": 150,
        "11": 150,
        "12": 150,
        "4": 150,
        "5": 150,
        "6": 150
      }
    },
    {
      "name": "荣耀Play4 Pro",
      "prices": {
        "1": 170,
        "11": 170,
        "12": 170,
        "4": 170,
        "5": 170,
        "6": 170
      }
    },
    {
      "name": "荣耀Play4t",
      "prices": {
        "1": 150,
        "11": 150,
        "12": 150,
        "4": 150,
        "5": 150,
        "6": 150
      }
    },
    {
      "name": "荣耀Play4",
      "prices": {
        "1": 170,
        "11": 170,
        "12": 170,
        "4": 170,
        "5": 170,
        "6": 170
      }
    },
    {
      "name": "荣耀Play3e",
      "prices": {
        "1": 75,
        "11": 75,
        "12": 75,
        "4": 75,
        "5": 75,
        "6": 75
      }
    },
    {
      "name": "荣耀Play3",
      "prices": {
        "1": 160,
        "11": 160,
        "12": 160,
        "4": 160,
        "5": 160,
        "6": 160
      }
    },
    {
      "name": "荣耀Play\n(6+64/6+128)",
      "prices": {
        "1": 80,
        "11": 80,
        "12": 80,
        "4": 80,
        "5": 80,
        "6": 80
      }
    },
    {
      "name": "荣耀Play(4+64)",
      "prices": {
        "1": 80,
        "11": 80,
        "12": 80,
        "4": 80,
        "5": 80,
        "6": 80
      }
    },
    {
      "name": "荣耀Magic7",
      "prices": {
        "1": 1300,
        "11": 1200,
        "12": 1000,
        "4": 900,
        "5": 400,
        "6": 400
      }
    },
    {
      "name": "荣耀Magic7pro",
      "prices": {
        "1": 1400,
        "11": 1300,
        "12": 1100,
        "4": 1000,
        "5": 400,
        "6": 400
      }
    },
    {
      "name": "荣耀Magic6Rs\n保时捷",
      "prices": {
        "1": 1200,
        "11": 1000,
        "12": 800,
        "4": 400,
        "5": 400,
        "6": 400
      }
    },
    {
      "name": "荣耀Magic6至臻",
      "prices": {
        "1": 1200,
        "11": 1000,
        "12": 800,
        "4": 600,
        "5": 400,
        "6": 400
      }
    },
    {
      "name": "荣耀Magic6pro",
      "prices": {
        "1": 900,
        "11": 800,
        "12": 700,
        "4": 600,
        "5": 300,
        "6": 300
      }
    },
    {
      "name": "荣耀Magic6",
      "prices": {
        "1": 550,
        "11": 500,
        "12": 400,
        "4": 300,
        "5": 300,
        "6": 300
      }
    },
    {
      "name": "荣耀Magic5至臻",
      "prices": {
        "1": 600,
        "11": 300,
        "12": 300,
        "4": 300,
        "5": 300,
        "6": 300
      }
    },
    {
      "name": "荣耀Magic5pro",
      "prices": {
        "1": 500,
        "11": 240,
        "12": 240,
        "4": 240,
        "5": 240,
        "6": 240
      }
    },
    {
      "name": "荣耀Magic5",
      "prices": {
        "1": 500,
        "11": 400,
        "12": 240,
        "4": 240,
        "5": 240,
        "6": 240
      }
    },
    {
      "name": "荣耀Magic4 至臻版",
      "prices": {
        "1": 300,
        "11": 300,
        "12": 300,
        "4": 300,
        "5": 300,
        "6": 300
      }
    },
    {
      "name": "荣耀Magic4 pro",
      "prices": {
        "1": 240,
        "11": 240,
        "12": 240,
        "4": 240,
        "5": 240,
        "6": 240
      }
    },
    {
      "name": "荣耀Magic4",
      "prices": {
        "1": 240,
        "11": 240,
        "12": 240,
        "4": 240,
        "5": 240,
        "6": 240
      }
    },
    {
      "name": "荣耀Magic3 Pro",
      "prices": {
        "1": 300,
        "11": 300,
        "12": 240,
        "4": 240,
        "5": 240,
        "6": 240
      }
    },
    {
      "name": "荣耀Magic3至臻版",
      "prices": {
        "1": 450,
        "11": 450,
        "12": 300,
        "4": 300,
        "5": 300,
        "6": 300
      }
    },
    {
      "name": "荣耀Magic3",
      "prices": {
        "1": 300,
        "11": 300,
        "12": 240,
        "4": 240,
        "5": 240,
        "6": 240
      }
    },
    {
      "name": "荣耀Magic2",
      "prices": {
        "1": 90,
        "11": 90,
        "12": 90,
        "4": 90,
        "5": 90,
        "6": 90
      }
    },
    {
      "name": "荣耀Magic",
      "prices": {
        "1": 40,
        "11": 40,
        "12": 40,
        "4": 40,
        "5": 40,
        "6": 40
      }
    },
    {
      "name": "畅玩60",
      "prices": {
        "1": 160,
        "11": 160,
        "12": 160,
        "4": 160,
        "5": 160,
        "6": 160
      }
    },
    {
      "name": "畅玩60plus",
      "prices": {
        "1": 300,
        "11": 300,
        "12": 300,
        "4": 300,
        "5": 250,
        "6": 250
      }
    },
    {
      "name": "畅玩50",
      "prices": {
        "1": 150,
        "11": 150,
        "12": 150,
        "4": 150,
        "5": 150,
        "6": 150
      }
    },
    {
      "name": "畅玩50plus",
      "prices": {
        "1": 280,
        "11": 280,
        "12": 280,
        "4": 280,
        "5": 200,
        "6": 200
      }
    },
    {
      "name": "畅玩40c",
      "prices": {
        "1": 150,
        "11": 150,
        "12": 150,
        "4": 150,
        "5": 150,
        "6": 150
      }
    },
    {
      "name": "畅玩40plus",
      "prices": {
        "1": 180,
        "11": 180,
        "12": 180,
        "4": 180,
        "5": 180,
        "6": 180
      }
    },
    {
      "name": "畅玩40S",
      "prices": {
        "1": 150,
        "11": 150,
        "12": 150,
        "4": 150,
        "5": 150,
        "6": 150
      }
    },
    {
      "name": "畅玩40",
      "prices": {
        "1": 150,
        "11": 150,
        "12": 150,
        "4": 150,
        "5": 150,
        "6": 150
      }
    },
    {
      "name": "畅玩30 PIUS",
      "prices": {
        "1": 160,
        "11": 160,
        "12": 160,
        "4": 160,
        "5": 160,
        "6": 160
      }
    },
    {
      "name": "畅玩30M",
      "prices": {
        "1": 150,
        "11": 150,
        "12": 150,
        "4": 150,
        "5": 150,
        "6": 150
      }
    },
    {
      "name": "畅玩30",
      "prices": {
        "1": 150,
        "11": 150,
        "12": 150,
        "4": 150,
        "5": 150,
        "6": 150
      }
    },
    {
      "name": "畅玩20 PRO",
      "prices": {
        "1": 200,
        "11": 200,
        "12": 200,
        "4": 200,
        "5": 200,
        "6": 200
      }
    },
    {
      "name": "畅玩20A",
      "prices": {
        "1": 150,
        "11": 150,
        "12": 150,
        "4": 150,
        "5": 150,
        "6": 150
      }
    },
    {
      "name": "畅玩20",
      "prices": {
        "1": 150,
        "11": 150,
        "12": 150,
        "4": 150,
        "5": 150,
        "6": 150
      }
    },
    {
      "name": "畅玩9a",
      "prices": {
        "1": 140,
        "11": 140,
        "12": 140,
        "4": 140,
        "5": 140,
        "6": 140
      }
    },
    {
      "name": "畅玩8x max",
      "prices": {
        "1": 110,
        "11": 110,
        "12": 110,
        "4": 110,
        "5": 110,
        "6": 110
      }
    },
    {
      "name": "畅玩8a(3+32)",
      "prices": {
        "1": 70,
        "11": 70,
        "12": 70,
        "4": 70,
        "5": 70,
        "6": 70
      }
    },
    {
      "name": "畅玩8a(3+64)",
      "prices": {
        "1": 90,
        "11": 90,
        "12": 90,
        "4": 90,
        "5": 90,
        "6": 90
      }
    },
    {
      "name": "畅玩8c",
      "prices": {
        "1": 80,
        "11": 80,
        "12": 80,
        "4": 80,
        "5": 80,
        "6": 80
      }
    },
    {
      "name": "畅玩8",
      "prices": {
        "1": 70,
        "11": 70,
        "12": 70,
        "4": 70,
        "5": 70,
        "6": 70
      }
    },
    {
      "name": "畅玩7a(3+32)",
      "prices": {
        "1": 60,
        "11": 60,
        "12": 60,
        "4": 60,
        "5": 60,
        "6": 60
      }
    },
    {
      "name": "畅玩7a(2+32)",
      "prices": {
        "1": 35,
        "11": 35,
        "12": 35,
        "4": 35,
        "5": 35,
        "6": 35
      }
    },
    {
      "name": "畅玩7x",
      "prices": {
        "1": 80,
        "11": 80,
        "12": 80,
        "4": 80,
        "5": 80,
        "6": 80
      }
    },
    {
      "name": "畅玩7c",
      "prices": {
        "1": 80,
        "11": 80,
        "12": 80,
        "4": 80,
        "5": 80,
        "6": 80
      }
    },
    {
      "name": "畅玩6x高配",
      "prices": {
        "1": 80,
        "11": 80,
        "12": 80,
        "4": 80,
        "5": 80,
        "6": 80
      }
    },
    {
      "name": "畅玩6x低配",
      "prices": {
        "1": 60,
        "11": 60,
        "12": 60,
        "4": 60,
        "5": 60,
        "6": 60
      }
    },
    {
      "name": "畅享80",
      "prices": {
        "1": 200,
        "11": 90,
        "12": 90,
        "4": 90,
        "5": 90,
        "6": 90
      }
    },
    {
      "name": "畅享70Z",
      "prices": {
        "1": 110,
        "11": 110,
        "12": 110,
        "4": 110,
        "5": 90,
        "6": 90
      }
    },
    {
      "name": "畅享70x",
      "prices": {
        "1": 200,
        "11": 200,
        "12": 90,
        "4": 90,
        "5": 90,
        "6": 90
      }
    },
    {
      "name": "畅享70 Pro",
      "prices": {
        "1": 220,
        "11": 220,
        "12": 220,
        "4": 220,
        "5": 200,
        "6": 200
      }
    },
    {
      "name": "畅享70s",
      "prices": {
        "1": 200,
        "11": 200,
        "12": 200,
        "4": 200,
        "5": 200,
        "6": 200
      }
    },
    {
      "name": "畅享70",
      "prices": {
        "1": 200,
        "11": 200,
        "12": 200,
        "4": 200,
        "5": 200,
        "6": 200
      }
    },
    {
      "name": "畅享60 Pro 4G",
      "prices": {
        "1": 160,
        "11": 160,
        "12": 160,
        "4": 160,
        "5": 160,
        "6": 160
      }
    },
    {
      "name": "畅享60X 4G",
      "prices": {
        "1": 240,
        "11": 240,
        "12": 240,
        "4": 240,
        "5": 200,
        "6": 200
      }
    },
    {
      "name": "畅享60",
      "prices": {
        "1": 160,
        "11": 160,
        "12": 160,
        "4": 160,
        "5": 120,
        "6": 120
      }
    },
    {
      "name": "畅享60s",
      "prices": {
        "1": 150,
        "11": 150,
        "12": 150,
        "4": 150,
        "5": 110,
        "6": 110
      }
    },
    {
      "name": "畅享50Pro",
      "prices": {
        "1": 160,
        "11": 160,
        "12": 160,
        "4": 160,
        "5": 160,
        "6": 160
      }
    },
    {
      "name": "畅享50Z",
      "prices": {
        "1": 160,
        "11": 160,
        "12": 160,
        "4": 160,
        "5": 160,
        "6": 160
      }
    },
    {
      "name": "畅享50(6+128)",
      "prices": {
        "1": 110,
        "11": 110,
        "12": 110,
        "4": 110,
        "5": 110,
        "6": 110
      }
    },
    {
      "name": "畅享50\n(8+128/8+256)",
      "prices": {
        "1": 120,
        "11": 120,
        "12": 120,
        "4": 120,
        "5": 120,
        "6": 80
      }
    },
    {
      "name": "畅享20Pro高配",
      "prices": {
        "1": 160,
        "11": 160,
        "12": 160,
        "4": 160,
        "5": 160,
        "6": 160
      }
    },
    {
      "name": "畅享20Pro低配",
      "prices": {
        "1": 150,
        "11": 150,
        "12": 150,
        "4": 150,
        "5": 150,
        "6": 150
      }
    },
    {
      "name": "畅享20Plus",
      "prices": {
        "1": 160,
        "11": 160,
        "12": 160,
        "4": 160,
        "5": 160,
        "6": 160
      }
    },
    {
      "name": "畅享20se",
      "prices": {
        "1": 160,
        "11": 160,
        "12": 160,
        "4": 160,
        "5": 160,
        "6": 160
      }
    },
    {
      "name": "畅享20E",
      "prices": {
        "1": 130,
        "11": 130,
        "12": 130,
        "4": 130,
        "5": 130,
        "6": 130
      }
    },
    {
      "name": "畅享20",
      "prices": {
        "1": 150,
        "11": 150,
        "12": 150,
        "4": 150,
        "5": 150,
        "6": 150
      }
    },
    {
      "name": "畅享10plus\n(6+128/8+128)",
      "prices": {
        "1": 150,
        "11": 150,
        "12": 150,
        "4": 150,
        "5": 150,
        "6": 150
      }
    },
    {
      "name": "畅享10plus\n(4+128)",
      "prices": {
        "1": 130,
        "11": 130,
        "12": 130,
        "4": 130,
        "5": 130,
        "6": 130
      }
    },
    {
      "name": "畅享10s",
      "prices": {
        "1": 150,
        "11": 150,
        "12": 150,
        "4": 150,
        "5": 150,
        "6": 150
      }
    },
    {
      "name": "畅享10e",
      "prices": {
        "1": 140,
        "11": 140,
        "12": 140,
        "4": 140,
        "5": 140,
        "6": 140
      }
    },
    {
      "name": "畅享10",
      "prices": {
        "1": 140,
        "11": 140,
        "12": 140,
        "4": 140,
        "5": 140,
        "6": 140
      }
    },
    {
      "name": "畅享9 plus",
      "prices": {
        "1": 120,
        "11": 120,
        "12": 120,
        "4": 120,
        "5": 120,
        "6": 120
      }
    },
    {
      "name": "畅享9e(3+32)",
      "prices": {
        "1": 75,
        "11": 75,
        "12": 75,
        "4": 75,
        "5": 75,
        "6": 75
      }
    },
    {
      "name": "畅享9e(3+64)",
      "prices": {
        "1": 90,
        "11": 90,
        "12": 90,
        "4": 90,
        "5": 90,
        "6": 90
      }
    },
    {
      "name": "畅享9s",
      "prices": {
        "1": 120,
        "11": 120,
        "12": 120,
        "4": 120,
        "5": 120,
        "6": 120
      }
    },
    {
      "name": "畅享9",
      "prices": {
        "1": 90,
        "11": 90,
        "12": 90,
        "4": 90,
        "5": 90,
        "6": 90
      }
    },
    {
      "name": "畅享8e(3+32)",
      "prices": {
        "1": 60,
        "11": 60,
        "12": 60,
        "4": 60,
        "5": 60,
        "6": 60
      }
    },
    {
      "name": "畅享8e(2+16)",
      "prices": {
        "1": 35,
        "11": 35,
        "12": 35,
        "4": 35,
        "5": 35,
        "6": 35
      }
    },
    {
      "name": "畅享8p",
      "prices": {
        "1": 80,
        "11": 80,
        "12": 80,
        "4": 80,
        "5": 80,
        "6": 80
      }
    },
    {
      "name": "畅享8",
      "prices": {
        "1": 80,
        "11": 80,
        "12": 80,
        "4": 80,
        "5": 80,
        "6": 80
      }
    },
    {
      "name": "畅享7s",
      "prices": {
        "1": 80,
        "11": 80,
        "12": 80,
        "4": 80,
        "5": 80,
        "6": 80
      }
    },
    {
      "name": "畅享7P高配",
      "prices": {
        "1": 80,
        "11": 80,
        "12": 80,
        "4": 80,
        "5": 80,
        "6": 80
      }
    },
    {
      "name": "畅享7P低配",
      "prices": {
        "1": 55,
        "11": 55,
        "12": 55,
        "4": 55,
        "5": 55,
        "6": 55
      }
    },
    {
      "name": "畅享6",
      "prices": {
        "1": 40,
        "11": 40,
        "12": 40,
        "4": 40,
        "5": 40,
        "6": 40
      }
    },
    {
      "name": "畅享max",
      "prices": {
        "1": 110,
        "11": 110,
        "12": 110,
        "4": 110,
        "5": 110,
        "6": 110
      }
    },
    {
      "name": "畅享Z\n(6+128/8+128)",
      "prices": {
        "1": 160,
        "11": 160,
        "12": 160,
        "4": 160,
        "5": 160,
        "6": 160
      }
    },
    {
      "name": "畅享Z(6+64)",
      "prices": {
        "1": 90,
        "11": 90,
        "12": 90,
        "4": 90,
        "5": 90,
        "6": 90
      }
    },
    {
      "name": "麦芒40",
      "prices": {
        "1": 260,
        "11": 220,
        "12": 220,
        "4": 220,
        "5": 140,
        "6": 140
      }
    },
    {
      "name": "麦芒30",
      "prices": {
        "1": 260,
        "11": 260,
        "12": 260,
        "4": 260,
        "5": 260,
        "6": 260
      }
    },
    {
      "name": "麦芒A205G",
      "prices": {
        "1": 150,
        "11": 150,
        "12": 150,
        "4": 150,
        "5": 150,
        "6": 150
      }
    },
    {
      "name": "麦芒205G",
      "prices": {
        "1": 260,
        "11": 260,
        "12": 260,
        "4": 260,
        "5": 260,
        "6": 260
      }
    },
    {
      "name": "麦芒11",
      "prices": {
        "1": 130,
        "11": 130,
        "12": 130,
        "4": 130,
        "5": 130,
        "6": 130
      }
    },
    {
      "name": "麦芒10se",
      "prices": {
        "1": 150,
        "11": 150,
        "12": 150,
        "4": 150,
        "5": 150,
        "6": 150
      }
    },
    {
      "name": "麦芒10",
      "prices": {
        "1": 200,
        "11": 200,
        "12": 200,
        "4": 200,
        "5": 200,
        "6": 200
      }
    },
    {
      "name": "麦芒9",
      "prices": {
        "1": 170,
        "11": 170,
        "12": 170,
        "4": 170,
        "5": 170,
        "6": 170
      }
    },
    {
      "name": "麦芒8",
      "prices": {
        "1": 130,
        "11": 130,
        "12": 130,
        "4": 130,
        "5": 130,
        "6": 130
      }
    },
    {
      "name": "麦芒7",
      "prices": {
        "1": 110,
        "11": 110,
        "12": 110,
        "4": 110,
        "5": 110,
        "6": 110
      }
    },
    {
      "name": "麦芒6",
      "prices": {
        "1": 90,
        "11": 90,
        "12": 90,
        "4": 90,
        "5": 90,
        "6": 90
      }
    },
    {
      "name": "麦芒5(4+64)",
      "prices": {
        "1": 100,
        "11": 100,
        "12": 100,
        "4": 100,
        "5": 100,
        "6": 100
      }
    },
    {
      "name": "麦芒5(3+32)",
      "prices": {
        "1": 55,
        "11": 55,
        "12": 55,
        "4": 55,
        "5": 55,
        "6": 55
      }
    },
    {
      "name": "G9plus",
      "prices": {
        "1": 50,
        "11": 50,
        "12": 50,
        "4": 50,
        "5": 50,
        "6": 50
      }
    },
    {
      "name": "G9",
      "prices": {
        "1": 25,
        "11": 25,
        "12": 25,
        "4": 25,
        "5": 25,
        "6": 25
      }
    },
    {
      "name": "荣耀V9play",
      "prices": {
        "1": 75,
        "11": 75,
        "12": 75,
        "4": 75,
        "5": 75,
        "6": 75
      }
    },
    {
      "name": "P8青春电信",
      "prices": {
        "1": 25,
        "11": 25,
        "12": 25,
        "4": 25,
        "5": 25,
        "6": 25
      }
    },
    {
      "name": "P8青春",
      "prices": {
        "1": 25,
        "11": 25,
        "12": 25,
        "4": 25,
        "5": 25,
        "6": 25
      }
    },
    {
      "name": "P8max",
      "prices": {
        "1": 25,
        "11": 25,
        "12": 25,
        "4": 25,
        "5": 25,
        "6": 25
      }
    },
    {
      "name": "P8标配",
      "prices": {
        "1": 25,
        "11": 25,
        "12": 25,
        "4": 25,
        "5": 25,
        "6": 25
      }
    },
    {
      "name": "P8电信",
      "prices": {
        "1": 25,
        "11": 25,
        "12": 25,
        "4": 25,
        "5": 25,
        "6": 25
      }
    },
    {
      "name": "畅享8e青春",
      "prices": {
        "1": 50,
        "11": 50,
        "12": 50,
        "4": 50,
        "5": 50,
        "6": 50
      }
    },
    {
      "name": "C8818",
      "prices": {
        "1": 25,
        "11": 25,
        "12": 25,
        "4": 25,
        "5": 25,
        "6": 25
      }
    },
    {
      "name": "C8817L",
      "prices": {
        "1": 10,
        "11": 10,
        "12": 10,
        "4": 10,
        "5": 10,
        "6": 10
      }
    },
    {
      "name": "C8817D",
      "prices": {
        "1": 15,
        "11": 15,
        "12": 15,
        "4": 15,
        "5": 15,
        "6": 15
      }
    },
    {
      "name": "C8815、C8816",
      "prices": {
        "1": 10,
        "11": 10,
        "12": 10,
        "4": 10,
        "5": 10,
        "6": 10
      }
    },
    {
      "name": "G750",
      "prices": {
        "1": 15,
        "11": 15,
        "12": 15,
        "4": 15,
        "5": 15,
        "6": 15
      }
    },
    {
      "name": "G730",
      "prices": {
        "1": 10,
        "11": 10,
        "12": 10,
        "4": 10,
        "5": 10,
        "6": 10
      }
    },
    {
      "name": "G7p",
      "prices": {
        "1": 25,
        "11": 25,
        "12": 25,
        "4": 25,
        "5": 25,
        "6": 25
      }
    },
    {
      "name": "荣耀7i金色",
      "prices": {
        "1": 45,
        "11": 45,
        "12": 45,
        "4": 45,
        "5": 45,
        "6": 45
      }
    },
    {
      "name": "荣耀7i白色",
      "prices": {
        "1": 25,
        "11": 25,
        "12": 25,
        "4": 25,
        "5": 25,
        "6": 25
      }
    },
    {
      "name": "畅玩7",
      "prices": {
        "1": 50,
        "11": 50,
        "12": 50,
        "4": 50,
        "5": 50,
        "6": 50
      }
    },
    {
      "name": "G629",
      "prices": {
        "1": 10,
        "11": 10,
        "12": 10,
        "4": 10,
        "5": 10,
        "6": 10
      }
    },
    {
      "name": "畅享7",
      "prices": {
        "1": 40,
        "11": 40,
        "12": 40,
        "4": 40,
        "5": 40,
        "6": 40
      }
    },
    {
      "name": "荣耀7",
      "prices": {
        "1": 30,
        "11": 30,
        "12": 30,
        "4": 30,
        "5": 30,
        "6": 30
      }
    },
    {
      "name": "荣耀7电信",
      "prices": {
        "1": 30,
        "11": 30,
        "12": 30,
        "4": 30,
        "5": 30,
        "6": 30
      }
    },
    {
      "name": "P7",
      "prices": {
        "1": 25,
        "11": 25,
        "12": 25,
        "4": 25,
        "5": 25,
        "6": 25
      }
    },
    {
      "name": "G628",
      "prices": {
        "1": 10,
        "11": 10,
        "12": 10,
        "4": 10,
        "5": 10,
        "6": 10
      }
    },
    {
      "name": "Mate7电信",
      "prices": {
        "1": 25,
        "11": 25,
        "12": 25,
        "4": 25,
        "5": 25,
        "6": 25
      }
    },
    {
      "name": "Mate7",
      "prices": {
        "1": 25,
        "11": 25,
        "12": 25,
        "4": 25,
        "5": 25,
        "6": 25
      }
    },
    {
      "name": "G7",
      "prices": {
        "1": 20,
        "11": 20,
        "12": 20,
        "4": 20,
        "5": 20,
        "6": 20
      }
    },
    {
      "name": "G621双卡",
      "prices": {
        "1": 15,
        "11": 15,
        "12": 15,
        "4": 15,
        "5": 15,
        "6": 15
      }
    },
    {
      "name": "G621单卡",
      "prices": {
        "1": 10,
        "11": 10,
        "12": 10,
        "4": 10,
        "5": 10,
        "6": 10
      }
    },
    {
      "name": "G620双卡",
      "prices": {
        "1": 15,
        "11": 15,
        "12": 15,
        "4": 15,
        "5": 15,
        "6": 15
      }
    },
    {
      "name": "G620单卡",
      "prices": {
        "1": 10,
        "11": 10,
        "12": 10,
        "4": 10,
        "5": 10,
        "6": 10
      }
    },
    {
      "name": "G620s",
      "prices": {
        "1": 15,
        "11": 15,
        "12": 15,
        "4": 15,
        "5": 15,
        "6": 15
      }
    },
    {
      "name": "G610",
      "prices": {
        "1": 10,
        "11": 10,
        "12": 10,
        "4": 10,
        "5": 10,
        "6": 10
      }
    },
    {
      "name": "6a",
      "prices": {
        "1": 40,
        "11": 40,
        "12": 40,
        "4": 40,
        "5": 40,
        "6": 40
      }
    },
    {
      "name": "荣耀6p",
      "prices": {
        "1": 25,
        "11": 25,
        "12": 25,
        "4": 25,
        "5": 25,
        "6": 25
      }
    },
    {
      "name": "荣耀6",
      "prices": {
        "1": 25,
        "11": 25,
        "12": 25,
        "4": 25,
        "5": 25,
        "6": 25
      }
    },
    {
      "name": "畅玩6",
      "prices": {
        "1": 35,
        "11": 35,
        "12": 35,
        "4": 35,
        "5": 35,
        "6": 35
      }
    },
    {
      "name": "畅享6S",
      "prices": {
        "1": 60,
        "11": 60,
        "12": 60,
        "4": 60,
        "5": 60,
        "6": 60
      }
    },
    {
      "name": "G6",
      "prices": {
        "1": 10,
        "11": 10,
        "12": 10,
        "4": 10,
        "5": 10,
        "6": 10
      }
    },
    {
      "name": "P6",
      "prices": {
        "1": 10,
        "11": 10,
        "12": 10,
        "4": 10,
        "5": 10,
        "6": 10
      }
    },
    {
      "name": "畅享5海外版",
      "prices": {
        "1": 25,
        "11": 25,
        "12": 25,
        "4": 25,
        "5": 25,
        "6": 25
      }
    },
    {
      "name": "畅享5",
      "prices": {
        "1": 35,
        "11": 35,
        "12": 35,
        "4": 35,
        "5": 35,
        "6": 35
      }
    },
    {
      "name": "5x移动",
      "prices": {
        "1": 30,
        "11": 30,
        "12": 30,
        "4": 30,
        "5": 30,
        "6": 30
      }
    },
    {
      "name": "5x全网",
      "prices": {
        "1": 30,
        "11": 30,
        "12": 30,
        "4": 30,
        "5": 30,
        "6": 30
      }
    },
    {
      "name": "5x电信",
      "prices": {
        "1": 30,
        "11": 30,
        "12": 30,
        "4": 30,
        "5": 30,
        "6": 30
      }
    },
    {
      "name": "5a移动",
      "prices": {
        "1": 30,
        "11": 30,
        "12": 30,
        "4": 30,
        "5": 30,
        "6": 30
      }
    },
    {
      "name": "5a全网",
      "prices": {
        "1": 30,
        "11": 30,
        "12": 30,
        "4": 30,
        "5": 30,
        "6": 30
      }
    },
    {
      "name": "畅玩5",
      "prices": {
        "1": 25,
        "11": 25,
        "12": 25,
        "4": 25,
        "5": 25,
        "6": 25
      }
    },
    {
      "name": "5x联通",
      "prices": {
        "1": 30,
        "11": 30,
        "12": 30,
        "4": 30,
        "5": 30,
        "6": 30
      }
    },
    {
      "name": "5s",
      "prices": {
        "1": 40,
        "11": 40,
        "12": 40,
        "4": 40,
        "5": 40,
        "6": 40
      }
    },
    {
      "name": "5c",
      "prices": {
        "1": 35,
        "11": 35,
        "12": 35,
        "4": 35,
        "5": 35,
        "6": 35
      }
    },
    {
      "name": "麦芒4电信",
      "prices": {
        "1": 25,
        "11": 25,
        "12": 25,
        "4": 25,
        "5": 25,
        "6": 25
      }
    },
    {
      "name": "麦芒4",
      "prices": {
        "1": 45,
        "11": 45,
        "12": 45,
        "4": 45,
        "5": 45,
        "6": 45
      }
    },
    {
      "name": "4a全网电信",
      "prices": {
        "1": 15,
        "11": 15,
        "12": 15,
        "4": 15,
        "5": 15,
        "6": 15
      }
    },
    {
      "name": "4c电信",
      "prices": {
        "1": 25,
        "11": 25,
        "12": 25,
        "4": 25,
        "5": 25,
        "6": 25
      }
    },
    {
      "name": "4x(2g)",
      "prices": {
        "1": 25,
        "11": 25,
        "12": 25,
        "4": 25,
        "5": 25,
        "6": 25
      }
    },
    {
      "name": "4x(che1)(全网)",
      "prices": {
        "1": 25,
        "11": 25,
        "12": 25,
        "4": 25,
        "5": 25,
        "6": 25
      }
    },
    {
      "name": "4x(1g)",
      "prices": {
        "1": 25,
        "11": 25,
        "12": 25,
        "4": 25,
        "5": 25,
        "6": 25
      }
    },
    {
      "name": "4c",
      "prices": {
        "1": 25,
        "11": 25,
        "12": 25,
        "4": 25,
        "5": 25,
        "6": 25
      }
    },
    {
      "name": "4a移动",
      "prices": {
        "1": 15,
        "11": 15,
        "12": 15,
        "4": 15,
        "5": 15,
        "6": 15
      }
    },
    {
      "name": "H30-u10",
      "prices": {
        "1": 10,
        "11": 10,
        "12": 10,
        "4": 10,
        "5": 10,
        "6": 10
      }
    },
    {
      "name": "H30-t00",
      "prices": {
        "1": 10,
        "12": 10,
        "4": 10,
        "5": 10,
        "6": 10
      }
    },
    {
      "name": "H30-t10",
      "prices": {
        "1": 10,
        "11": 10,
        "12": 10,
        "4": 10,
        "5": 10,
        "6": 10
      }
    },
    {
      "name": "H30",
      "prices": {
        "1": 10,
        "11": 10,
        "12": 10,
        "4": 10,
        "5": 10,
        "6": 10
      }
    },
    {
      "name": "Mate2",
      "prices": {
        "1": 15,
        "11": 15,
        "12": 15,
        "4": 15,
        "5": 15,
        "6": 15
      }
    },
    {
      "name": "Matel",
      "prices": {
        "1": 10,
        "11": 10,
        "12": 10,
        "4": 10,
        "5": 10,
        "6": 10
      }
    },
    {
      "name": "A199",
      "prices": {
        "1": 10,
        "11": 10,
        "12": 10,
        "4": 10,
        "5": 10,
        "6": 10
      }
    },
    {
      "name": "B199",
      "prices": {
        "1": 15,
        "11": 15,
        "12": 15,
        "4": 15,
        "5": 15,
        "6": 15
      }
    },
    {
      "name": "C199",
      "prices": {
        "1": 20,
        "11": 20,
        "12": 20,
        "4": 20,
        "5": 20,
        "6": 20
      }
    },
    {
      "name": "Gx1金色",
      "prices": {
        "1": 10,
        "11": 10,
        "12": 10,
        "4": 10,
        "5": 10,
        "6": 10
      }
    },
    {
      "name": "Gx1白色",
      "prices": {
        "1": 10,
        "11": 10,
        "12": 10,
        "4": 10,
        "5": 10,
        "6": 10
      }
    },
    {
      "name": "HOL",
      "prices": {
        "1": 10,
        "11": 10,
        "12": 10,
        "4": 10,
        "5": 10,
        "6": 10
      }
    },
    {
      "name": "C8812/C8813",
      "prices": {
        "1": 10,
        "11": 10,
        "12": 10,
        "4": 10,
        "5": 10,
        "6": 10
      }
    }
  ],
  "brand_id": 9,
  "total": 489
}